extractreq/__init__.py
extractreq/modul_ekspart.py
extractreq/modul_spacySent.py
extractreq/modul_stanfordSent.py
extractreq/modul_triplet.py
extractreq/usecase_modul1.py
extractreq/usecase_modul2.py
extractreq/usecase_modul3.py
extractreq-0.0.9.dist-info/LICENSE
extractreq-0.0.9.dist-info/METADATA
extractreq-0.0.9.dist-info/WHEEL
extractreq-0.0.9.dist-info/top_level.txt
extractreq-0.0.9.dist-info/RECORD
