Metadata-Version: 2.1
Name: extractreq
Version: 0.0.9
Summary: Berikut ini deskripsi singkat pembuatan ekstraksi kebutuhan
Home-page: https://github.com/asyrofist/Extraction-Requirement
Author: asyrofist (Rakha Asyrofi)
Author-email: rakhasyrofist@gmail.com
License: UNKNOWN
Project-URL: Bug Tracker, https://github.com/asyrofist/Extraction-Requirement/issues
Platform: UNKNOWN
Classifier: Programming Language :: Python :: 3
Classifier: License :: OSI Approved :: MIT License
Classifier: Operating System :: OS Independent
Requires-Python: >=3.6
License-File: LICENSE
